LICENSE
MANIFEST.in
README.md
setup.cfg
setup.py
TESTE_topologic.egg-info/PKG-INFO
TESTE_topologic.egg-info/SOURCES.txt
TESTE_topologic.egg-info/dependency_links.txt
TESTE_topologic.egg-info/requires.txt
TESTE_topologic.egg-info/top_level.txt
pytopomat/__init__.py
pytopomat/analyzer.py
pytopomat/irrep_caller.py
pytopomat/irvsp_caller.py
pytopomat/symmorphic_spacegroups.json
pytopomat/vasp2trace_caller.py
pytopomat/z2pack_caller.py
pytopomat/workflows/__init__.py
pytopomat/workflows/core.py
pytopomat/workflows/firetasks.py
pytopomat/workflows/fireworks.py
pytopomat/workflows/irrep.yaml
pytopomat/workflows/irvsp.yaml
pytopomat/workflows/irvsp_v2t.yaml
pytopomat/workflows/irvsp_v2t_magnetic.yaml
pytopomat/workflows/vasp2trace_magnetic.yaml
pytopomat/workflows/vasp2trace_nonmagnetic.yaml
pytopomat/workflows/z2pack.yaml